Metadata-Version: 2.1
Name: oslo-core
Version: 2.0.2
Summary: OSLO: Open Source framework for Large-scale transformer Optimization
Home-page: https://github.com/tunib-ai/oslo
Author: TUNiB OSLO Team
Author-email: contact@tunib.ai
License: UNKNOWN
Platform: UNKNOWN
Classifier: Programming Language :: Python :: 3.6
Classifier: Programming Language :: Python :: 3.7
Classifier: Programming Language :: Python :: 3.8
Classifier: Programming Language :: Python :: 3.9
Classifier: Intended Audience :: Developers
Classifier: Intended Audience :: Science/Research
Classifier: Topic :: Scientific/Engineering :: Artificial Intelligence
Requires-Python: >=3.6.0
